marblex/__init__.py
marblex/client.py
marblex/http.py
marblex/models.py
marblex.py-1.0.0a0.dist-info/LICENSE
marblex.py-1.0.0a0.dist-info/METADATA
marblex.py-1.0.0a0.dist-info/WHEEL
marblex.py-1.0.0a0.dist-info/top_level.txt
marblex.py-1.0.0a0.dist-info/RECORD
