Metadata-Version: 2.1
Name: marblex.py
Version: 1.0.0a0
Summary: A library to get various cryptocurrency prices from the marblex API
Home-page: https://github.com/staciax/marblex.py
Author: xStacia
Author-email: "marblex.py" <ixximm.11820@gmail.com>
License: MIT License        
Project-URL: Homepage, https://github.com/staciax/marblex.py
Project-URL: Bug Tracker, https://github.com/staciax/marblex.py/issues
Keywords: marblex,ninokuni,nft
Classifier: License :: OSI Approved :: MIT License
Classifier: Intended Audience :: Developers
Classifier: Natural Language :: English
Classifier: Operating System :: OS Independent
Classifier: Programming Language :: Python :: 3
Classifier: Programming Language :: Python :: 3.8
Classifier: Programming Language :: Python :: 3.9
Classifier: Programming Language :: Python :: 3.10
Classifier: Programming Language :: Python :: 3.11
Classifier: Topic :: Internet :: WWW/HTTP
Requires-Python: >=3.6.0
License-File: LICENSE
Requires-Dist: requests
